imgProfiler/App.py
imgProfiler/App_2.py
imgProfiler/Sift_keypoints.py
imgProfiler/TEST.py
imgProfiler/__init__.py
imgProfiler/delete.py
imgProfiler/features.py
imgProfiler/readrr.py
imgProfiler/symmetry.py
imgProfiler/tempCodeRunnerFile.py
imgProfiler/transformation.py
imgProfiler-0.1.0.dist-info/METADATA
imgProfiler-0.1.0.dist-info/WHEEL
imgProfiler-0.1.0.dist-info/top_level.txt
imgProfiler-0.1.0.dist-info/RECORD
