Metadata-Version: 2.1
Name: imgProfiler
Version: 0.1.0
Summary: Image profiling library
Author: @itertools
